[{"pic-url": "//images.albertsons-media.com/is/image/ABS/970123994?$ecom-product-card-desktop-jpg$&defaultImage=Not_Available", "price": "$1.00", "name": "Haribo Goldbears Pineapple - 4 OZ", "unit-price": "$3.98 / Pound", "rating": "None"},
{"pic-url": "//images.albertsons-media.com/is/image/ABS/970470171?$ecom-product-card-desktop-jpg$&defaultImage=Not_Available", "price": "$1.00", "name": "Spindrift Pineapple Sparkling Water - 12 Fl. Oz.", "unit-price": "$10.67 / Gal.", "rating": "None"},
{"pic-url": "//images.albertsons-media.com/is/image/ABS/960040864?$ecom-product-card-desktop-jpg$&defaultImage=Not_Available", "price": "$1.25", "name": "Jarritos Pineapple - 12.5 Fl. Oz.", "unit-price": "$12.80 / Gal.", "rating": "None"},
{"pic-url": "//images.albertsons-media.com/is/image/ABS/960085294?$ecom-product-card-desktop-jpg$&defaultImage=Not_Available", "price": "$1.25", "name": "Sparkling Ice Coconut Pineapple Sparkling Water 17 fl. oz. Bottle", "unit-price": "$9.41 / Gal.", "rating": "None"},
{"pic-url": "//images.albertsons-media.com/is/image/ABS/960323816?$ecom-product-card-desktop-jpg$&defaultImage=Not_Available", "price": "$1.25", "name": "BODYARMOR Pineapple Coconut Sports Drink - 16 Fl. Oz.", "unit-price": "$10.00 / Gal.", "rating": "None"},
{"pic-url": "//images.albertsons-media.com/is/image/ABS/960281252?$ecom-product-card-desktop-jpg$&defaultImage=Not_Available", "price": "$1.25", "name": "hint Water Infused With Pineapple - 16 Fl. Oz.", "unit-price": "$10.00 / Gal.", "rating": "None"},
{"pic-url": "//images.albertsons-media.com/is/image/ABS/960331735?$ecom-product-card-desktop-jpg$&defaultImage=Not_Available", "price": "$1.25", "name": "Polar Seltzer Pineapple Pomelo - 1 Liter", "unit-price": "$4.73 / Gal.", "rating": "None"},
{"pic-url": "//images.albertsons-media.com/is/image/ABS/960170987?$ecom-product-card-desktop-jpg$&defaultImage=Not_Available", "price": "$1.33", "name": "Beech-Nut Naturals Stage 2 Banana Orange & Pineapple Baby Food - 4 Oz", "unit-price": "$5.33 / Pound", "rating": "None"},
{"pic-url": "//images.albertsons-media.com/is/image/ABS/108050900?$ecom-product-card-desktop-jpg$&defaultImage=Not_Available", "price": "$1.39", "name": "Goya Refresco Soda Pineapple Bottle - 12 Oz", "unit-price": "$14.83 / Gal.", "rating": "None"},
{"pic-url": "//images.albertsons-media.com/is/image/ABS/122400018?$ecom-product-card-desktop-jpg$&defaultImage=Not_Available", "price": "$1.49", "name": "Dole Pineapple Chunks in 100% Pineapple Juice - 8 Oz", "unit-price": "$2.98 / Pound", "rating": "None"},
{"pic-url": "//images.albertsons-media.com/is/image/ABS/122400019?$ecom-product-card-desktop-jpg$&defaultImage=Not_Available", "price": "$1.49", "name": "Dole Pineapple Tidbits in Pineapple Juice - 8 Oz", "unit-price": "$2.98 / Pound", "rating": "None"},
{"pic-url": "//images.albertsons-media.com/is/image/ABS/122400017?$ecom-product-card-desktop-jpg$&defaultImage=Not_Available", "price": "$1.49", "name": "Dole Pineapple Slices in 100% Pineapple Juice - 8 Oz", "unit-price": "$2.98 / Pound", "rating": "None"},
{"pic-url": "//images.albertsons-media.com/is/image/ABS/122400020?$ecom-product-card-desktop-jpg$&defaultImage=Not_Available", "price": "$1.49", "name": "Dole Pineapple Crushed in 100% Pineapple Juice - 8 Oz", "unit-price": "$2.98 / Pound", "rating": "None"},
{"pic-url": "//images.albertsons-media.com/is/image/ABS/960428244?$ecom-product-card-desktop-jpg$&defaultImage=Not_Available", "price": "$1.49", "name": "Goya Wafer Pineapple - 4.94 Oz", "unit-price": "$4.83 / Pound", "rating": "None"},
{"pic-url": "//images.albertsons-media.com/is/image/ABS/960046038?$ecom-product-card-desktop-jpg$&defaultImage=Not_Available", "price": "$1.49", "name": "Goya Juice Drink Pineapple Can - 9.6 Oz", "unit-price": "$19.87 / Gal.", "rating": "None"},
{"pic-url": "//images.albertsons-media.com/is/image/ABS/960541679?$ecom-product-card-desktop-jpg$&defaultImage=Not_Available", "price": "$1.50", "name": "smartwater Vapor Distilled Water Pineapple Kiwi - 23.7 Fl. Oz.", "unit-price": "$8.10 / Gal.", "rating": "None"},
{"pic-url": "//images.albertsons-media.com/is/image/ABS/960086040?$ecom-product-card-desktop-jpg$&defaultImage=Not_Available", "price": "$1.50", "name": "coco libre Coconut Water Organic with Pineapple - 11 Fl. Oz.", "unit-price": "$5.68 / Gal.", "rating": "None"},
{"pic-url": "//images.albertsons-media.com/is/image/ABS/960174701?$ecom-product-card-desktop-jpg$&defaultImage=Not_Available", "price": "$1.67", "name": "Del Monte Pineapple Tidbits in its Own Juice - 15.25 Oz", "unit-price": "$1.75 / Pound", "rating": "None"},
{"pic-url": "//images.albertsons-media.com/is/image/ABS/960174691?$ecom-product-card-desktop-jpg$&defaultImage=Not_Available", "price": "$1.67", "name": "Del Monte Juice Pineapple Chunks Natural - 15.25 Oz", "unit-price": "$1.75 / Pound", "rating": "None"},
{"pic-url": "//images.albertsons-media.com/is/image/ABS/960174692?$ecom-product-card-desktop-jpg$&defaultImage=Not_Available", "price": "$1.67", "name": "Del Monte Juice Pineapple Crushed Natural - 15.25 Oz", "unit-price": "$1.75 / Pound", "rating": "None"},
{"pic-url": "//images.albertsons-media.com/is/image/ABS/960049985?$ecom-product-card-desktop-jpg$&defaultImage=Not_Available", "price": "$1.67", "name": "Chobani Yogurt Greek Fruit On The Bottom Low-Fat Pineapple - 5.3 Oz", "unit-price": "$5.03 / Pound", "rating": "None"},
{"pic-url": "//images.albertsons-media.com/is/image/ABS/970031328?$ecom-product-card-desktop-jpg$&defaultImage=Not_Available", "price": "$1.67", "name": "Daisy 4% Cottage Cheese With Pineapple - 5.3 OZ", "unit-price": "$4.45 / Pound", "rating": "None"},
{"pic-url": "//images.albertsons-media.com/is/image/ABS/960333648?$ecom-product-card-desktop-jpg$&defaultImage=Not_Available", "price": "$1.67", "name": "Hood Cottage Cheese With Pineapple Single Serve - 5.3 Oz", "unit-price": "$5.04 / Pound", "rating": "None"},
{"pic-url": "//images.albertsons-media.com/is/image/ABS/960279599?$ecom-product-card-desktop-jpg$&defaultImage=Not_Available", "price": "$1.67", "name": "Del Monte Juice Pineapple Slices Natural - 15.25 Oz", "unit-price": "$1.75 / Pound", "rating": "None"},
{"pic-url": "//images.albertsons-media.com/is/image/ABS/960228706?$ecom-product-card-desktop-jpg$&defaultImage=Not_Available", "price": "$1.67", "name": "Bai Antioxidant Cocofusion Puna Coconut Pineapple Coconut Flavored Water Bottle - 18 Fl. Oz.", "unit-price": "$11.88 / Gal.", "rating": "None"},
{"pic-url": "//images.albertsons-media.com/is/image/ABS/960552954?$ecom-product-card-desktop-jpg$&defaultImage=Not_Available", "price": "$1.67", "name": "Yerbae Yerba Mate Zero Platform Pnapl - 16 Oz", "unit-price": "$13.36 / Gal.", "rating": "None"},
{"pic-url": "//images.albertsons-media.com/is/image/ABS/970042714?$ecom-product-card-desktop-jpg$&defaultImage=Not_Available", "price": "$1.79", "name": "Propel Water Beverage With Immune Support Pineapple Peach - 24 Fl. Oz.", "unit-price": "$9.55 / Gal.", "rating": "None"},
{"pic-url": "//images.albertsons-media.com/is/image/ABS/122400010?$ecom-product-card-desktop-jpg$&defaultImage=Not_Available", "price": "$1.99", "name": "Dole Pineapple Chunks in 100% Pineapple Juice - 20 Oz", "unit-price": "$1.59 / Pound", "rating": "None"},
{"pic-url": "//images.albertsons-media.com/is/image/ABS/122400011?$ecom-product-card-desktop-jpg$&defaultImage=Not_Available", "price": "$1.99", "name": "Dole Pineapple Tidbits in 100% Pineapple Juice - 20 Oz", "unit-price": "$1.59 / Pound", "rating": "None"},
{"pic-url": "//images.albertsons-media.com/is/image/ABS/122400009?$ecom-product-card-desktop-jpg$&defaultImage=Not_Available", "price": "$1.99", "name": "Dole Pineapple Slices in 100% Pineapple Juice - 20 Oz", "unit-price": "$1.59 / Pound", "rating": "None"}]